flake8_pydocstyle/__init__.py
flake8_pydocstyle/generic_types.py
flake8_pydocstyle/metadata.py
flake8_pydocstyle/plugin.py
flake8_pydocstyle-0.2.5.dist-info/entry_points.txt
flake8_pydocstyle-0.2.5.dist-info/LICENSE
flake8_pydocstyle-0.2.5.dist-info/METADATA
flake8_pydocstyle-0.2.5.dist-info/NOTICE
flake8_pydocstyle-0.2.5.dist-info/WHEEL
flake8_pydocstyle-0.2.5.dist-info/RECORD
