Metadata-Version: 2.1
Name: flake8-pydocstyle
Version: 0.2.5
Summary: flake8 plugin that integrates pydocstyle
Home-page: https://github.com/KRunchPL/flake8-pydocstyle
License: Apache-2.0
Author: KRunchPL
Author-email: krunchfrompoland@gmail.com
Requires-Python: >=3.8.1,<4.0.0
Classifier: License :: OSI Approved :: Apache Software License
Classifier: Programming Language :: Python :: 3
Classifier: Programming Language :: Python :: 3.9
Classifier: Programming Language :: Python :: 3.10
Classifier: Programming Language :: Python :: 3.11
Classifier: Programming Language :: Python :: 3.12
Classifier: Programming Language :: Python :: 3.13
Requires-Dist: pydocstyle (>=6.3.0,<7.0.0)
Project-URL: Documentation, https://github.com/KRunchPL/flake8-pydocstyle
Project-URL: Repository, https://github.com/KRunchPL/flake8-pydocstyle
